[
  {
    "@context": "https://schema.org",
    "@type": "WebPage",
    "@id": "https://construction-project-02.netlify.app/legal/regulamin.html#webpage",
    "name": "Regulamin serwisu - Axiom Construction",
    "description": "Regulamin serwisu Axiom Construction, w tym zasady korzystania z wersji demo, odpowiedzialność oraz kontakt w sprawach formalnych.",
    "url": "https://construction-project-02.netlify.app/legal/regulamin.html",
    "inLanguage": "pl-PL",
    "isPartOf": {
      "@type": "WebSite",
      "@id": "https://construction-project-02.netlify.app/#website"
    },
    "breadcrumb": {
      "@id": "https://construction-project-02.netlify.app/legal/regulamin.html#breadcrumbs"
    }
  },
  {
    "@context": "https://schema.org",
    "@type": "BreadcrumbList",
    "@id": "https://construction-project-02.netlify.app/legal/regulamin.html#breadcrumbs",
    "itemListElement": [
      {
        "@type": "ListItem",
        "position": 1,
        "name": "Strona główna",
        "item": "https://construction-project-02.netlify.app/"
      },
      {
        "@type": "ListItem",
        "position": 2,
        "name": "Regulamin serwisu",
        "item": "https://construction-project-02.netlify.app/legal/regulamin.html"
      }
    ]
  }
]
